pnd/__init__.py
pnd/apathy.py
pnd/boredom.py
pnd/specific.py
pnp/__init__.py
pnp/crime.py
pnp/tragedy.py
PoliticsAndData-1.2.0.dist-info/LICENSE.txt
PoliticsAndData-1.2.0.dist-info/METADATA
PoliticsAndData-1.2.0.dist-info/WHEEL
PoliticsAndData-1.2.0.dist-info/top_level.txt
PoliticsAndData-1.2.0.dist-info/RECORD
