Metadata-Version: 2.1
Name: PoliticsAndData
Version: 1.2.0
Summary: Easily summarize the csv data files from https://politicsandwar.com/data/
Home-page: https://github.com/pythonian23/PoliticsAndData
Author: pythonian23
License: MPL-2.0
Platform: UNKNOWN
Requires: requests
Requires: pytz
Requires: numpy
License-File: LICENSE.txt
